CometTS/ARIMA.py
CometTS/CSV_It.py
CometTS/CometTS.py
CometTS/Plotting.py
CometTS/__init__.py
CometTS/Landsat_Expansion_Docs_HelperScripts/LS_Untar.bash
CometTS/Landsat_Expansion_Docs_HelperScripts/Landsat_Expansion_CometTS_UsersGuide.docx
CometTS/Landsat_Expansion_Docs_HelperScripts/Landsat_PixelQA_CloudMasking_MultiDir.ipynb
CometTS/VIIRS_Sample/Raster_List.csv
CometTS/VIIRS_Sample/San_Juan.cpg
CometTS/VIIRS_Sample/San_Juan.dbf
CometTS/VIIRS_Sample/San_Juan.prj
CometTS/VIIRS_Sample/San_Juan.qpj
CometTS/VIIRS_Sample/San_Juan.shp
CometTS/VIIRS_Sample/San_Juan.shx
CometTS/VIIRS_Sample/San_Juan_ARIMA_Output.csv
CometTS/VIIRS_Sample/San_Juan_FullStats.csv
CometTS/VIIRS_Sample/San_Juan_Stats_ID_1.csv
CometTS/VIIRS_Sample/Test_Raster_List.csv
CometTS/VIIRS_Sample/Test_Raster_List2.csv
CometTS/VIIRS_Sample/Test_San_Juan_ARIMA_Output.csv
CometTS/VIIRS_Sample/Test_San_Juan_FullStats.csv
CometTS/VIIRS_Sample/Test_San_Juan_FullStats2.csv
CometTS/VIIRS_Sample/temp1.vrt
CometTS/VIIRS_Sample/temp2.vrt
CometTS/VIIRS_Sample/SVDNB_npp_20160701-20160731_75N180W_vcmcfg_v10_c201609121310/SVDNB_npp_20160701-20160731_75N180W_vcmcfg_v10_c201609121310.avg_rade9_clip.tif
CometTS/VIIRS_Sample/SVDNB_npp_20160701-20160731_75N180W_vcmcfg_v10_c201609121310/SVDNB_npp_20160701-20160731_75N180W_vcmcfg_v10_c201609121310.cf_cvg_clip.tif
CometTS/VIIRS_Sample/SVDNB_npp_20160801-20160831_75N180W_vcmcfg_v10_c201610041107/SVDNB_npp_20160801-20160831_75N180W_vcmcfg_v10_c201610041107.avg_rade9_clip.tif
CometTS/VIIRS_Sample/SVDNB_npp_20160801-20160831_75N180W_vcmcfg_v10_c201610041107/SVDNB_npp_20160801-20160831_75N180W_vcmcfg_v10_c201610041107.cf_cvg_clip.tif
CometTS/VIIRS_Sample/SVDNB_npp_20160901-20160930_75N180W_vcmcfg_v10_c201610280941/SVDNB_npp_20160901-20160930_75N180W_vcmcfg_v10_c201610280941.avg_rade9_clip.tif
CometTS/VIIRS_Sample/SVDNB_npp_20160901-20160930_75N180W_vcmcfg_v10_c201610280941/SVDNB_npp_20160901-20160930_75N180W_vcmcfg_v10_c201610280941.cf_cvg_clip.tif
CometTS-1.2.0.dist-info/LICENSE
CometTS-1.2.0.dist-info/METADATA
CometTS-1.2.0.dist-info/WHEEL
CometTS-1.2.0.dist-info/entry_points.txt
CometTS-1.2.0.dist-info/top_level.txt
CometTS-1.2.0.dist-info/RECORD
